odoo/addons/shopinvader_search_engine_image/README.rst
odoo/addons/shopinvader_search_engine_image/__init__.py
odoo/addons/shopinvader_search_engine_image/__manifest__.py
odoo/addons/shopinvader_search_engine_image/demo/fs_product_image.xml
odoo/addons/shopinvader_search_engine_image/demo/image_tag.xml
odoo/addons/shopinvader_search_engine_image/demo/se_thumbnail_size.xml
odoo/addons/shopinvader_search_engine_image/i18n/shopinvader_search_engine_image.pot
odoo/addons/shopinvader_search_engine_image/models/__init__.py
odoo/addons/shopinvader_search_engine_image/models/se_backend.py
odoo/addons/shopinvader_search_engine_image/readme/CONTRIBUTORS.rst
odoo/addons/shopinvader_search_engine_image/readme/DESCRIPTION.rst
odoo/addons/shopinvader_search_engine_image/readme/HISTORY.rst
odoo/addons/shopinvader_search_engine_image/readme/USAGE.rst
odoo/addons/shopinvader_search_engine_image/readme/newsfragments/.gitignore
odoo/addons/shopinvader_search_engine_image/schemas/__init__.py
odoo/addons/shopinvader_search_engine_image/schemas/image_data.py
odoo/addons/shopinvader_search_engine_image/schemas/images_mixin.py
odoo/addons/shopinvader_search_engine_image/schemas/product_category.py
odoo/addons/shopinvader_search_engine_image/schemas/product_product.py
odoo/addons/shopinvader_search_engine_image/static/description/index.html
odoo/addons/shopinvader_search_engine_image/static/img/2be1238822f7edbc3b3c5f64c6e12f36ec84c861_chathm001gry_uk_thelma_dining_chairs_oak_grey07-524.jpg
odoo/addons/shopinvader_search_engine_image/static/img/51gnjksrxml_sl1024_-497.jpg
odoo/addons/shopinvader_search_engine_image/static/img/5c7f91a29eb6294768ad59bbce80ed04fcaff33d_chathm001gry_uk_thelma_dining_chairs_oak_grey02-515.jpg
odoo/addons/shopinvader_search_engine_image/static/img/61kcwirwmjl_sl1500_-289.jpg
odoo/addons/shopinvader_search_engine_image/static/img/61ncsqkegrl_sl1500_-298.jpg
odoo/addons/shopinvader_search_engine_image/static/img/61vffbcilbl_sl1500_-292.jpg
odoo_addon_shopinvader_search_engine_image-16.0.1.0.4.dist-info/METADATA
odoo_addon_shopinvader_search_engine_image-16.0.1.0.4.dist-info/WHEEL
odoo_addon_shopinvader_search_engine_image-16.0.1.0.4.dist-info/top_level.txt
odoo_addon_shopinvader_search_engine_image-16.0.1.0.4.dist-info/RECORD
